xl_link/__init__.py
xl_link/chart_wrapper.py
xl_link/mappers.py
xl_link/xl_types/__init__.py
xl_link/xl_types/xl_types.py
xl_link/xlsxwriter/__init__.py
xl_link/xlsxwriter/utility.py
xl_link-0.133.dist-info/DESCRIPTION.rst
xl_link-0.133.dist-info/METADATA
xl_link-0.133.dist-info/RECORD
xl_link-0.133.dist-info/WHEEL
xl_link-0.133.dist-info/metadata.json
xl_link-0.133.dist-info/top_level.txt
