Metadata-Version: 2.0
Name: xl-link
Version: 0.133
Summary: Excel spreadsheets made easy through Pandas magic
Home-page: https://github.com/0Hughman0/xl_link
Author: Hugh Ramsden
Author-email: hugh.o.ramsden@gmail.com
License: MIT
Download-URL: https://github.com/0Hughman0/xl_link/archive/0.133.tar.gz
Keywords: pandas,excel,io,data,charts,graphs
Platform: UNKNOWN
Requires-Python: >=3.4
Provides-Extra: openpyxl
Provides-Extra: xlsxwriter
Requires-Dist: pandas (>=0.19)
Provides-Extra: openpyxl
Requires-Dist: openpyxl (>=2.4); extra == 'openpyxl'
Provides-Extra: xlsxwriter
Requires-Dist: xslxwriter (>=0.9); extra == 'xlsxwriter'
